import_future_annotations/__init__.py
import_future_annotations/__main__.py
import_future_annotations-1.0.0.dist-info/licenses/LICENSE
import_future_annotations-1.0.0.dist-info/METADATA
import_future_annotations-1.0.0.dist-info/WHEEL
import_future_annotations-1.0.0.dist-info/entry_points.txt
import_future_annotations-1.0.0.dist-info/top_level.txt
import_future_annotations-1.0.0.dist-info/RECORD
