Metadata-Version: 2.4
Name: import_future_annotations
Version: 1.0.0
Summary: Add import responsible for postponed evaluation of annotations to python files
Home-page: https://github.com/mbroton/import-future-annotations
Author: Michal Broton
Author-email: michal@broton.dev
Classifier: Programming Language :: Python :: 3
Classifier: Programming Language :: Python :: 3 :: Only
Classifier: Programming Language :: Python :: Implementation :: CPython
Classifier: Programming Language :: Python :: Implementation :: PyPy
Requires-Python: >=3.8
License-File: LICENSE
Requires-Dist: classify-imports>=4.1
Dynamic: license-file
